.coveragerc
.env
.travis.yml
CHANGES.rst
CONTRIBUTING.md
LICENSE
MANIFEST.in
README-configobj.md
README.md
dev-requirements.txt
setup.cfg
setup.py
setup_validate.py
tasks.py
tox.ini
validate.py
docs/Makefile
docs/conf.py
docs/configobj.html
docs/configobj.rst
docs/default.css
docs/docutils.conf
docs/docutils.css
docs/index.rst
docs/make.bat
docs/pygments.css
docs/template.txt
docs/validate.html
docs/validate.rst
docs/_static/css/custom.css
src/configobj/__init__.py
src/configobj/_version.py
src/configobj/validate.py
src/configobj_dev.egg-info/PKG-INFO
src/configobj_dev.egg-info/SOURCES.txt
src/configobj_dev.egg-info/dependency_links.txt
src/configobj_dev.egg-info/requires.txt
src/configobj_dev.egg-info/top_level.txt
src/tests/__init__.py
src/tests/conf.ini
src/tests/conf.spec
src/tests/configobj_doctests.py
src/tests/conftest.py
src/tests/test_configobj.py
src/tests/test_validate.py
src/tests/test_validate_errors.py